{
    "MesEncodeIncrementalHandleCreate": [
        {
            "name": "UserState",
            "type": "void"
        },
        {
            "name": "AllocFn",
            "type": "MIDL_ES_ALLOC"
        },
        {
            "name": "WriteFn",
            "type": "MIDL_ES_WRITE"
        },
        {
            "name": "pHandle",
            "type": "handle_t"
        }
    ],
    "MesDecodeIncrementalHandleCreate": [
        {
            "name": "UserState",
            "type": "void"
        },
        {
            "name": "ReadFn",
            "type": "MIDL_ES_READ"
        },
        {
            "name": "pHandle",
            "type": "handle_t"
        }
    ],
    "MesIncrementalHandleReset": [
        {
            "name": "Handle",
            "type": "handle_t"
        },
        {
            "name": "UserState",
            "type": "void"
        },
        {
            "name": "AllocFn",
            "type": "MIDL_ES_ALLOC"
        },
        {
            "name": "WriteFn",
            "type": "MIDL_ES_WRITE"
        },
        {
            "name": "ReadFn",
            "type": "MIDL_ES_READ"
        },
        {
            "name": "Operation",
            "type": "MIDL_ES_CODE"
        }
    ],
    "MesEncodeFixedBufferHandleCreate": [
        {
            "name": "pBuffer",
            "type": "char"
        },
        {
            "name": "BufferSize",
            "type": "unsigned long"
        },
        {
            "name": "pEncodedSize",
            "type": "unsigned long"
        },
        {
            "name": "pHandle",
            "type": "handle_t"
        }
    ],
    "MesEncodeDynBufferHandleCreate": [
        {
            "name": "pBuffer",
            "type": "char"
        },
        {
            "name": "pEncodedSize",
            "type": "unsigned long"
        },
        {
            "name": "pHandle",
            "type": "handle_t"
        }
    ],
    "MesDecodeBufferHandleCreate": [
        {
            "name": "Buffer",
            "type": "char"
        },
        {
            "name": "BufferSize",
            "type": "unsigned long"
        },
        {
            "name": "pHandle",
            "type": "handle_t"
        }
    ],
    "MesBufferHandleReset": [
        {
            "name": "Handle",
            "type": "handle_t"
        },
        {
            "name": "HandleStyle",
            "type": "unsigned long"
        },
        {
            "name": "Operation",
            "type": "MIDL_ES_CODE"
        },
        {
            "name": "pBuffer",
            "type": "char"
        },
        {
            "name": "BufferSize",
            "type": "unsigned long"
        },
        {
            "name": "pEncodedSize",
            "type": "unsigned long"
        }
    ],
    "MesHandleFree": [
        {
            "name": "Handle",
            "type": "handle_t"
        }
    ],
    "MesInqProcEncodingId": [
        {
            "name": "Handle",
            "type": "handle_t"
        },
        {
            "name": "pInterfaceId",
            "type": "PRPC_SYNTAX_IDENTIFIER"
        },
        {
            "name": "pProcNum",
            "type": "unsigned long"
        }
    ],
    "NdrMesProcEncodeDecode2": [
        {
            "name": "Handle",
            "type": "handle_t"
        },
        {
            "name": "pStubDesc",
            "type": "MIDL_STUB_DESC"
        },
        {
            "name": "pFormatString",
            "type": "PFORMAT_STRING"
        }
    ]
}